qtsix-1.1.dist-info/top_level.txt
qtsix-1.1.dist-info/RECORD
qtsix-1.1.dist-info/METADATA
qtsix-1.1.dist-info/WHEEL
qtsix-1.1.dist-info/DESCRIPTION.rst
qtsix-1.1.dist-info/metadata.json
qtsix/QtOpenGL.py
qtsix/QtNetwork.py
qtsix/QtXml.py
qtsix/QtDBus.py
qtsix/uic.py
qtsix/QtTest.py
qtsix/QtCore.py
qtsix/QtSvg.py
qtsix/QtPrintSupport.py
qtsix/QtMultimedia.py
qtsix/QtWidgets.py
qtsix/QtXmlPatterns.py
qtsix/QtDesigner.py
qtsix/Qsci.py
qtsix/Qt.py
qtsix/QtGui.py
qtsix/QtSql.py
qtsix/QtHelp.py
qtsix/QtWebKit.py
qtsix/QtWebKitWidgets.py
qtsix/__init__.py
qtsix/QAxContainer.py
