Metadata-Version: 2.0
Name: qtsix
Version: 1.1
Summary: Compatibility layer for different Qt bindings.
Home-page: https://github.com/avalentino/qtsix
Author: Antonio Valentino
Author-email: antonio.valentino@tiscali.it
License: BSD
Keywords: Qt bindings
Platform: UNKNOWN
Classifier: Development Status :: 4 - Beta
Classifier: Intended Audience :: Developers
Classifier: Topic :: Software Development :: Widget Sets
Classifier: License :: OSI Approved :: BSD License
Classifier: Programming Language :: Python :: 2
Classifier: Programming Language :: Python :: 2.6
Classifier: Programming Language :: Python :: 2.7
Classifier: Programming Language :: Python :: 3
Classifier: Programming Language :: Python :: 3.2
Classifier: Programming Language :: Python :: 3.3
Classifier: Programming Language :: Python :: 3.4
